odoo/addons/hr_timesheet_task_stage/README.rst
odoo/addons/hr_timesheet_task_stage/__init__.py
odoo/addons/hr_timesheet_task_stage/__manifest__.py
odoo/addons/hr_timesheet_task_stage/i18n/hr_timesheet_task_stage.pot
odoo/addons/hr_timesheet_task_stage/models/__init__.py
odoo/addons/hr_timesheet_task_stage/models/account_analytic_line.py
odoo/addons/hr_timesheet_task_stage/readme/CONTRIBUTORS.rst
odoo/addons/hr_timesheet_task_stage/readme/DESCRIPTION.rst
odoo/addons/hr_timesheet_task_stage/static/description/icon.png
odoo/addons/hr_timesheet_task_stage/static/description/index.html
odoo/addons/hr_timesheet_task_stage/tests/__init__.py
odoo/addons/hr_timesheet_task_stage/tests/test_hr_timesheet_task_stage.py
odoo/addons/hr_timesheet_task_stage/views/account_analytic_line.xml
odoo11_addon_hr_timesheet_task_stage-11.0.1.0.1.dist-info/METADATA
odoo11_addon_hr_timesheet_task_stage-11.0.1.0.1.dist-info/WHEEL
odoo11_addon_hr_timesheet_task_stage-11.0.1.0.1.dist-info/top_level.txt
odoo11_addon_hr_timesheet_task_stage-11.0.1.0.1.dist-info/RECORD
